gunicorn_config.py
avgangstider/__init__.py
avgangstider/classes.py
avgangstider/constants.py
avgangstider/entur_api.py
avgangstider/entur_query.py
avgangstider/flask_app.py
avgangstider/py.typed
avgangstider/static/jquery-3.4.1.min.js
avgangstider/static/jquery.divslideshow-1.2-min.js
avgangstider/static/css/dinfont.css
avgangstider/static/css/sismonitor_single.css
avgangstider/static/fonts/Din/DIN-Bold-webfont.eot
avgangstider/static/fonts/Din/DIN-Bold-webfont.ttf
avgangstider/static/fonts/Din/DIN-Bold-webfont.woff
avgangstider/static/fonts/Din/DIN-Regular-webfont.eot
avgangstider/static/fonts/Din/DIN-Regular-webfont.ttf
avgangstider/static/fonts/Din/DIN-Regular-webfont.woff
avgangstider/static/fonts/Din/din-medium.eot
avgangstider/static/fonts/Din/din-medium.ttf
avgangstider/static/fonts/Din/din-medium.woff
avgangstider/templates/avgangstider.html
avgangstider/templates/departure_table.html
avgangstider/templates/help.html
avgangstider-0.9.21.dist-info/METADATA
avgangstider-0.9.21.dist-info/WHEEL
avgangstider-0.9.21.dist-info/top_level.txt
avgangstider-0.9.21.dist-info/RECORD
