Metadata-Version: 2.2
Name: avgangstider
Version: 0.9.21
Summary: Avgangstider fra EnTur
Author-email: Martin Høy <martin@hoy.priv.no>
Requires-Python: >=3.10
Requires-Dist: loguru>=0.7.3
Requires-Dist: pydantic>=2.10.6
Requires-Dist: requests>=2.32.3
Requires-Dist: flask>=3.1.0
Requires-Dist: gunicorn>=23.0.0
